simhandler/__init__.py
simhandler/datageneration.py
simhandler/powerflowsim.py
simhandler/powersystemnetwork.py
simhandler/regressiontools.py
simhandler/smartsim.py
simhandler/data/__init__.py
simhandler/data/function_mappings/__init__.py
simhandler/data/loadgen_profiles/__init__.py
simhandler/data/loadgen_profiles/example1.zp
simhandler/data/loadgen_profiles/example2.zp
simhandler/data/loadgen_profiles/example3.zp
simhandler/data/network_configurations/3node.json
simhandler/data/network_configurations/__init__.py
simhandler/test/__init__.py
simhandler/test/checkmodel.py
simhandler/test/thesis_tests/__init__.py
simhandler/test/thesis_tests/ann_analysis.py
simhandler/test/thesis_tests/hyperparameter_analysis.py
simhandler/test/thesis_tests/parametric_analysis.py
simhandler/test/thesis_tests/polyfitting_learning_curves.py
simhandler/utils/__init__.py
simhandler/utils/us_census_male_names.txt
simhandler-1.0.1.dist-info/METADATA
simhandler-1.0.1.dist-info/RECORD
simhandler-1.0.1.dist-info/WHEEL
simhandler-1.0.1.dist-info/top_level.txt
