Metadata-Version: 2.1
Name: simhandler
Version: 1.0.1
Summary: Intelligent simulation handler for power system load flow simulations
Home-page: https://github.com/mbardwell/intelligent-simulation-handler
Author: Mike Bardwell
Author-email: bardwell@ualberta.ca
License: GPL
Platform: UNKNOWN
Classifier: License :: OSI Approved :: GNU General Public License v3 (GPLv3)
Classifier: Programming Language :: Python :: 3.5
Classifier: Operating System :: Microsoft :: Windows
Classifier: Topic :: Scientific/Engineering :: Artificial Intelligence
Classifier: Intended Audience :: Science/Research
Classifier: Natural Language :: English
Requires-Python: >=3.5.0
Requires-Dist: numpy
Requires-Dist: matplotlib
Requires-Dist: h5py
Requires-Dist: tensorflow
Requires-Dist: keras
Requires-Dist: pypsa
